limitcalculator.py
limitcalculator-0.1.dist-info/LICENSE
limitcalculator-0.1.dist-info/WHEEL
limitcalculator-0.1.dist-info/METADATA
limitcalculator-0.1.dist-info/RECORD
