Metadata-Version: 2.1
Name: limitcalculator
Version: 0.1
Summary: A simple 
Author-email: tejas <tejas9patil@gmail.com>
Classifier: License :: OSI Approved :: MIT License
